{
  " 240619599": {
    "name": " eebeff",
    "tel": " 240619599"
  },
  " 369430613": {
    "name": " ccbfdf",
    "tel": " 369430613"
  },
  " 038085477": {
    "name": " acabcf",
    "tel": " 038085477"
  },
  " 096835687": {
    "name": " aedcab",
    "tel": " 096835687"
  },
  " 831250648": {
    "name": " ceface",
    "tel": " 831250648"
  },
  " 952019076": {
    "name": " abdeed",
    "tel": " 952019076"
  },
  " 369495067": {
    "name": " fbeccc",
    "tel": " 369495067"
  },
  " 746515889": {
    "name": " eaccda",
    "tel": " 746515889"
  },
  " 023953562": {
    "name": " cbdace",
    "tel": " 023953562"
  },
  " 037995457": {
    "name": " afbdad",
    "tel": " 037995457"
  }
}